ml_edu/__init__.py
ml_edu/experiment.py
ml_edu/results.py
google_ml_edu-0.1.3.dist-info/licenses/LICENSE
google_ml_edu-0.1.3.dist-info/WHEEL
google_ml_edu-0.1.3.dist-info/METADATA
google_ml_edu-0.1.3.dist-info/RECORD
